SupervisedDiscretization/__init__.py
SupervisedDiscretization/discretizer.py
SupervisedDiscretization/CounterfactualAnalysis/GradientBoostingSolver.py
SupervisedDiscretization/CounterfactualAnalysis/RandomForestSolver.py
SupervisedDiscretization/CounterfactualAnalysis/SVCSolver.py
SupervisedDiscretization/CounterfactualAnalysis/TreeEnsembleSolver.py
SupervisedDiscretization/CounterfactualAnalysis/__init__.py
SupervisedDiscretization/CounterfactualAnalysis/counterfactualExplanations.py
SupervisedDiscretization/CounterfactualAnalysis/gurobiSolver.py
SupervisedDiscretization-0.0.7.dist-info/LICENSE
SupervisedDiscretization-0.0.7.dist-info/METADATA
SupervisedDiscretization-0.0.7.dist-info/WHEEL
SupervisedDiscretization-0.0.7.dist-info/top_level.txt
SupervisedDiscretization-0.0.7.dist-info/RECORD
