Metadata-Version: 2.1
Name: SupervisedDiscretization
Version: 0.0.7
Author-email: Cecilia Salvatore <cecilia.salvatore@uniroma2.it>
Classifier: Programming Language :: Python :: 3
Classifier: License :: OSI Approved :: MIT License
Classifier: Operating System :: OS Independent
Requires-Python: >=3.7
License-File: LICENSE
